forex_calendar/__init__.py
forex_calendar/fetcher.py
fx_calendar-0.2.1.dist-info/licenses/LICENSE
fx_calendar-0.2.1.dist-info/METADATA
fx_calendar-0.2.1.dist-info/WHEEL
fx_calendar-0.2.1.dist-info/top_level.txt
fx_calendar-0.2.1.dist-info/RECORD
