Metadata-Version: 2.4
Name: fx-calendar
Version: 0.2.1
Summary: Forex Factory weekly calendar collector with CSV export, filters, and summaries.
Author: Rusznyak Peter
License: MIT License
Project-URL: Homepage, https://github.com/PetiRu/forex_calendar_project
Project-URL: Issues, https://github.com/PetiRu/forex_calendar_project/issues
Keywords: forex,economics,calendar,pandas,data-collection
Requires-Python: >=3.9
License-File: LICENSE
Requires-Dist: pandas>=1.5
Requires-Dist: requests>=2.28
Dynamic: license-file
